{
    "total": 43.9367,
    "sub": [
        {
            "class_name": "Charge",
            "sub": [
                {
                "name": "Pulay_mixing",
                "cpu_second": 0.0081662773154676,
                "calls": 8,
                "cpu_second_per_call": 0.001020784664433,
                "cpu_second_per_total": 0.000185864617654
                },
                {
                "name": "atomic_rho",
                "cpu_second": 0.210137706482783,
                "calls": 1,
                "cpu_second_per_call": 0.210137706482783,
                "cpu_second_per_total": 0.004782737955283
                },
                {
                "name": "mix_rho",
                "cpu_second": 0.0205293616745621,
                "calls": 8,
                "cpu_second_per_call": 0.002566170209320,
                "cpu_second_per_total": 0.000467248638629
                },
                {
                "name": "set_rho_core",
                "cpu_second": 2.10802536457777e-05,
                "calls": 1,
                "cpu_second_per_call": 0.000021080253646,
                "cpu_second_per_total": 0.000000479786950
                }
            ]
        },
        {
            "class_name": "Charge_Mixing",
            "sub": [
                {
                "name": "get_drho",
                "cpu_second": 0.0140995825640857,
                "calls": 9,
                "cpu_second_per_call": 0.001566620284898,
                "cpu_second_per_total": 0.000320906751157
                },
                {
                "name": "init_mixing",
                "cpu_second": 2.46590934693813e-06,
                "calls": 1,
                "cpu_second_per_call": 0.000002465909347,
                "cpu_second_per_total": 0.000000056124141
                },
                {
                "name": "inner_product_recip_hartree",
                "cpu_second": 0.00784930307418108,
                "calls": 36,
                "cpu_second_per_call": 0.000218036196505,
                "cpu_second_per_total": 0.000178650278257
                },
                {
                "name": "inner_product_recip_rho",
                "cpu_second": 0.00200204411521554,
                "calls": 9,
                "cpu_second_per_call": 0.000222449346135,
                "cpu_second_per_total": 0.000045566559844
                }
            ]
        },
        {
            "class_name": "DiagoCG",
            "sub": [
                {
                "name": "diag_once",
                "cpu_second": 28.5832074885257,
                "calls": 1998,
                "cpu_second_per_call": 0.014305909653917,
                "cpu_second_per_total": 0.650554313298895
                }
            ]
        },
        {
            "class_name": "DiagoCG_New",
            "sub": [
                {
                "name": "hpsi_func",
                "cpu_second": 25.284360792255,
                "calls": 89884,
                "cpu_second_per_call": 0.000281299906460,
                "cpu_second_per_total": 0.575472503532368
                },
                {
                "name": "spsi_func",
                "cpu_second": 0.204861663281918,
                "calls": 179768,
                "cpu_second_per_call": 0.000001139589155,
                "cpu_second_per_total": 0.004662655117734
                }
            ]
        },
        {
            "class_name": "DiagoIterAssist",
            "sub": [
                {
                "name": "diagH_LAPACK",
                "cpu_second": 0.120652462355793,
                "calls": 1998,
                "cpu_second_per_call": 0.000060386617796,
                "cpu_second_per_total": 0.002746052199607
                },
                {
                "name": "diagH_subspace",
                "cpu_second": 6.57733393739909,
                "calls": 1998,
                "cpu_second_per_call": 0.003291958927627,
                "cpu_second_per_total": 0.149700237970140
                }
            ]
        },
        {
            "class_name": "Driver",
            "sub": [
                {
                "name": "driver_line",
                "cpu_second": 43.8915764440317,
                "calls": 1,
                "cpu_second_per_call": 43.891576444031671,
                "cpu_second_per_total": 0.998973064328611
                },
                {
                "name": "reading",
                "cpu_second": 0.0450241265352815,
                "calls": 1,
                "cpu_second_per_call": 0.045024126535282,
                "cpu_second_per_total": 0.001024749924647
                }
            ]
        },
        {
            "class_name": "ESolver_KS_PW",
            "sub": [
                {
                "name": "hamilt2density",
                "cpu_second": 42.9093122954946,
                "calls": 9,
                "cpu_second_per_call": 4.767701366166067,
                "cpu_second_per_total": 0.976616714752162
                },
                {
                "name": "runner",
                "cpu_second": 43.4507056162693,
                "calls": 1,
                "cpu_second_per_call": 43.450705616269261,
                "cpu_second_per_total": 0.988938836409172
                }
            ]
        },
        {
            "class_name": "ElecStatePW",
            "sub": [
                {
                "name": "psiToRho",
                "cpu_second": 4.2320688739419,
                "calls": 9,
                "cpu_second_per_call": 0.470229874882433,
                "cpu_second_per_total": 0.096321963209557
                }
            ]
        },
        {
            "class_name": "HSolverPW",
            "sub": [
                {
                "name": "solve",
                "cpu_second": 42.6714508743025,
                "calls": 9,
                "cpu_second_per_call": 4.741272319366948,
                "cpu_second_per_total": 0.971202984554597
                }
            ]
        },
        {
            "class_name": "H_Ewald_pw",
            "sub": [
                {
                "name": "compute_ewald",
                "cpu_second": 0.000918568577617407,
                "calls": 1,
                "cpu_second_per_call": 0.000918568577617,
                "cpu_second_per_total": 0.000020906637244
                }
            ]
        },
        {
            "class_name": "H_Hartree_pw",
            "sub": [
                {
                "name": "v_hartree",
                "cpu_second": 0.014726193388924,
                "calls": 10,
                "cpu_second_per_call": 0.001472619338892,
                "cpu_second_per_total": 0.000335168424729
                }
            ]
        },
        {
            "class_name": "Input_Conv",
            "sub": [
                {
                "name": "Convert",
                "cpu_second": 0.000298902159556746,
                "calls": 1,
                "cpu_second_per_call": 0.000298902159557,
                "cpu_second_per_total": 0.000006803018494
                }
            ]
        },
        {
            "class_name": "Ions",
            "sub": [
                {
                "name": "opt_ions",
                "cpu_second": 43.4507332250942,
                "calls": 1,
                "cpu_second_per_call": 43.450733225094154,
                "cpu_second_per_total": 0.988939464786520
                }
            ]
        },
        {
            "class_name": "ModuleIO",
            "sub": [
                {
                "name": "write_istate_info",
                "cpu_second": 0.0295635128859431,
                "calls": 1,
                "cpu_second_per_call": 0.029563512885943,
                "cpu_second_per_total": 0.000672866081665
                }
            ]
        },
        {
            "class_name": "Nonlocal",
            "sub": [
                {
                "name": "getvnl",
                "cpu_second": 0.000422945711761713,
                "calls": 1998,
                "cpu_second_per_call": 0.000000211684540,
                "cpu_second_per_total": 0.000009626251959
                }
            ]
        },
        {
            "class_name": "Operator",
            "sub": [
                {
                "name": "EkineticPW",
                "cpu_second": 1.21154462685809,
                "calls": 91882,
                "cpu_second_per_call": 0.000013185875654,
                "cpu_second_per_total": 0.027574777360904
                },
                {
                "name": "NonlocalPW",
                "cpu_second": 0.0131304457318038,
                "calls": 91882,
                "cpu_second_per_call": 0.000000142905528,
                "cpu_second_per_total": 0.000298849179533
                },
                {
                "name": "VeffPW",
                "cpu_second": 29.9319319489878,
                "calls": 91882,
                "cpu_second_per_call": 0.000325764915315,
                "cpu_second_per_total": 0.681251306124406
                },
                {
                "name": "hPsi",
                "cpu_second": 31.2302560210228,
                "calls": 91882,
                "cpu_second_per_call": 0.000339895257189,
                "cpu_second_per_total": 0.710801185208523
                }
            ]
        },
        {
            "class_name": "PW_Basis",
            "sub": [
                {
                "name": "setup_struc_factor",
                "cpu_second": 0.0028885118663311,
                "calls": 1,
                "cpu_second_per_call": 0.002888511866331,
                "cpu_second_per_total": 0.000065742581703
                }
            ]
        },
        {
            "class_name": "PW_Basis_K",
            "sub": [
                {
                "name": "distributeg",
                "cpu_second": 0.000927987741306424,
                "calls": 1,
                "cpu_second_per_call": 0.000927987741306,
                "cpu_second_per_total": 0.000021121017578
                },
                {
                "name": "gatherp_scatters",
                "cpu_second": 4.27315064379945,
                "calls": 111862,
                "cpu_second_per_call": 0.000038200198850,
                "cpu_second_per_total": 0.097256985025758
                },
                {
                "name": "gathers_scatterp",
                "cpu_second": 6.64222445013002,
                "calls": 133840,
                "cpu_second_per_call": 0.000049628096609,
                "cpu_second_per_total": 0.151177147199667
                },
                {
                "name": "real2recip",
                "cpu_second": 12.98623333266,
                "calls": 111862,
                "cpu_second_per_call": 0.000116091553277,
                "cpu_second_per_total": 0.295566902750831
                },
                {
                "name": "recip2real",
                "cpu_second": 17.7493467205204,
                "calls": 133840,
                "cpu_second_per_call": 0.000132616159000,
                "cpu_second_per_total": 0.403975448588389
                },
                {
                "name": "setuptransform",
                "cpu_second": 0.00806478061713278,
                "calls": 1,
                "cpu_second_per_call": 0.008064780617133,
                "cpu_second_per_total": 0.000183554550986
                }
            ]
        },
        {
            "class_name": "PW_Basis_Sup",
            "sub": [
                {
                "name": "distributeg",
                "cpu_second": 0.000988632906228304,
                "calls": 1,
                "cpu_second_per_call": 0.000988632906228,
                "cpu_second_per_total": 0.000022501302615
                },
                {
                "name": "gatherp_scatters",
                "cpu_second": 0.0451397367287427,
                "calls": 108,
                "cpu_second_per_call": 0.000417960525266,
                "cpu_second_per_total": 0.001027381214717
                },
                {
                "name": "gathers_scatterp",
                "cpu_second": 0.162514871684834,
                "calls": 80,
                "cpu_second_per_call": 0.002031435896060,
                "cpu_second_per_total": 0.003698841384132
                },
                {
                "name": "real2recip",
                "cpu_second": 0.0737614051904529,
                "calls": 108,
                "cpu_second_per_call": 0.000682975973986,
                "cpu_second_per_total": 0.001678810900453
                },
                {
                "name": "recip2real",
                "cpu_second": 0.184348210226744,
                "calls": 80,
                "cpu_second_per_call": 0.002304352627834,
                "cpu_second_per_total": 0.004195768559567
                },
                {
                "name": "setuptransform",
                "cpu_second": 0.00449326378293335,
                "calls": 1,
                "cpu_second_per_call": 0.004493263782933,
                "cpu_second_per_total": 0.000102266764006
                }
            ]
        },
        {
            "class_name": "PotLocal",
            "sub": [
                {
                "name": "cal_fixed_v",
                "cpu_second": 0.000864282017573714,
                "calls": 1,
                "cpu_second_per_call": 0.000864282017574,
                "cpu_second_per_total": 0.000019671074167
                }
            ]
        },
        {
            "class_name": "PotXC",
            "sub": [
                {
                "name": "cal_v_eff",
                "cpu_second": 0.171001743758097,
                "calls": 10,
                "cpu_second_per_call": 0.017100174375810,
                "cpu_second_per_total": 0.003892002744203
                }
            ]
        },
        {
            "class_name": "Potential",
            "sub": [
                {
                "name": "cal_fixed_v",
                "cpu_second": 0.000885369954630733,
                "calls": 1,
                "cpu_second_per_call": 0.000885369954631,
                "cpu_second_per_total": 0.000020151035991
                },
                {
                "name": "cal_v_eff",
                "cpu_second": 0.186369598377496,
                "calls": 10,
                "cpu_second_per_call": 0.018636959837750,
                "cpu_second_per_total": 0.004241775390006
                },
                {
                "name": "init_pot",
                "cpu_second": 0.0208167536184192,
                "calls": 1,
                "cpu_second_per_call": 0.020816753618419,
                "cpu_second_per_total": 0.000473789684408
                },
                {
                "name": "interpolate_vrs",
                "cpu_second": 0.000324902590364218,
                "calls": 10,
                "cpu_second_per_call": 0.000032490259036,
                "cpu_second_per_total": 0.000007394788764
                },
                {
                "name": "update_from_charge",
                "cpu_second": 0.187624556478113,
                "calls": 10,
                "cpu_second_per_call": 0.018762455647811,
                "cpu_second_per_total": 0.004270338258806
                }
            ]
        },
        {
            "class_name": "Symmetry",
            "sub": [
                {
                "name": "analy_sys",
                "cpu_second": 0.0289146795403212,
                "calls": 1,
                "cpu_second_per_call": 0.028914679540321,
                "cpu_second_per_total": 0.000658098623122
                },
                {
                "name": "group fft grids",
                "cpu_second": 0.0558005755301565,
                "calls": 10,
                "cpu_second_per_call": 0.005580057553016,
                "cpu_second_per_total": 0.001270022096375
                },
                {
                "name": "rhog_symmetry",
                "cpu_second": 0.207176575902849,
                "calls": 10,
                "cpu_second_per_call": 0.020717657590285,
                "cpu_second_per_total": 0.004715342570361
                }
            ]
        },
        {
            "class_name": "UnitCell",
            "sub": [
                {
                "name": "check_tau",
                "cpu_second": 6.36093318462372e-07,
                "calls": 1,
                "cpu_second_per_call": 0.000000636093318,
                "cpu_second_per_total": 0.000000014477495
                }
            ]
        },
        {
            "class_name": "WF_atomic",
            "sub": [
                {
                "name": "init_at_1",
                "cpu_second": 1.7647398635745e-05,
                "calls": 1,
                "cpu_second_per_call": 0.000017647398636,
                "cpu_second_per_total": 0.000000401655108
                }
            ]
        },
        {
            "class_name": "XC_Functional",
            "sub": [
                {
                "name": "v_xc",
                "cpu_second": 26.8643353325315,
                "calls": 5,
                "cpu_second_per_call": 5.372867066506297,
                "cpu_second_per_total": 0.611432752307524
                },
                {
                "name": "v_xc_libxc",
                "cpu_second": 0.170683985576034,
                "calls": 10,
                "cpu_second_per_call": 0.017068398557603,
                "cpu_second_per_total": 0.003884770562300
                }
            ]
        },
        {
            "class_name": "mymath",
            "sub": [
                {
                "name": "heapsort",
                "cpu_second": 0.00171625730581582,
                "calls": 177,
                "cpu_second_per_call": 0.000009696368959,
                "cpu_second_per_total": 0.000039062046955
                }
            ]
        },
        {
            "class_name": "ppcell_vl",
            "sub": [
                {
                "name": "init_vloc",
                "cpu_second": 0.0694170317146927,
                "calls": 1,
                "cpu_second_per_call": 0.069417031714693,
                "cpu_second_per_total": 0.001579932882499
                }
            ]
        },
        {
            "class_name": "ppcell_vnl",
            "sub": [
                {
                "name": "init",
                "cpu_second": 1.59852206707001e-05,
                "calls": 1,
                "cpu_second_per_call": 0.000015985220671,
                "cpu_second_per_total": 0.000000363823908
                },
                {
                "name": "init_vnl",
                "cpu_second": 0.108978788135573,
                "calls": 1,
                "cpu_second_per_call": 0.108978788135573,
                "cpu_second_per_total": 0.002480359165714
                }
            ]
        },
        {
            "class_name": "wavefunc",
            "sub": [
                {
                "name": "wfcinit",
                "cpu_second": 3.64473089575768e-06,
                "calls": 1,
                "cpu_second_per_call": 0.000003644730896,
                "cpu_second_per_total": 0.000000082954140
                }
            ]
        }
    ]
}
