{
    "total": 8.72484,
    "sub": [
        {
            "class_name": "Charge",
            "sub": [
                {
                "name": "atomic_rho",
                "cpu_second": 0.0139922463567927,
                "calls": 2,
                "cpu_second_per_call": 0.006996123178396,
                "cpu_second_per_total": 0.001603725265210
                },
                {
                "name": "set_rho_core",
                "cpu_second": 8.37085535749793e-05,
                "calls": 2,
                "cpu_second_per_call": 0.000041854276787,
                "cpu_second_per_total": 0.000009594279493
                }
            ]
        },
        {
            "class_name": "Driver",
            "sub": [
                {
                "name": "driver_line",
                "cpu_second": 8.69538759347051,
                "calls": 1,
                "cpu_second_per_call": 8.695387593470514,
                "cpu_second_per_total": 0.996624303121436
                },
                {
                "name": "reading",
                "cpu_second": 0.0294522769981995,
                "calls": 1,
                "cpu_second_per_call": 0.029452276998200,
                "cpu_second_per_total": 0.003375681040453
                }
            ]
        },
        {
            "class_name": "ESolver_OF",
            "sub": [
                {
                "name": "runner",
                "cpu_second": 5.33453520946205,
                "calls": 1,
                "cpu_second_per_call": 5.334535209462047,
                "cpu_second_per_total": 0.611419258596262
                }
            ]
        },
        {
            "class_name": "H_Ewald_pw",
            "sub": [
                {
                "name": "compute_ewald",
                "cpu_second": 0.000510513898916543,
                "calls": 1,
                "cpu_second_per_call": 0.000510513898917,
                "cpu_second_per_total": 0.000058512694606
                }
            ]
        },
        {
            "class_name": "H_Hartree_pw",
            "sub": [
                {
                "name": "v_hartree",
                "cpu_second": 0.116333357524127,
                "calls": 216,
                "cpu_second_per_call": 0.000538580358908,
                "cpu_second_per_total": 0.013333580605345
                }
            ]
        },
        {
            "class_name": "Input",
            "sub": [
                {
                "name": "Init",
                "cpu_second": 0.0176816887687892,
                "calls": 1,
                "cpu_second_per_call": 0.017681688768789,
                "cpu_second_per_total": 0.002026591748531
                }
            ]
        },
        {
            "class_name": "Input_Conv",
            "sub": [
                {
                "name": "Convert",
                "cpu_second": 0.000300796004012227,
                "calls": 1,
                "cpu_second_per_call": 0.000300796004012,
                "cpu_second_per_total": 0.000034475818893
                }
            ]
        },
        {
            "class_name": "Ions",
            "sub": [
                {
                "name": "opt_ions",
                "cpu_second": 5.3345721954247,
                "calls": 1,
                "cpu_second_per_call": 5.334572195424698,
                "cpu_second_per_total": 0.611423497752809
                }
            ]
        },
        {
            "class_name": "KEDF_ML",
            "sub": [
                {
                "name": "Backward",
                "cpu_second": 0.156617207685485,
                "calls": 214,
                "cpu_second_per_call": 0.000731856110680,
                "cpu_second_per_total": 0.017950725460885
                },
                {
                "name": "Forward",
                "cpu_second": 0.133250563521869,
                "calls": 214,
                "cpu_second_per_call": 0.000622666184682,
                "cpu_second_per_total": 0.015272550945313
                },
                {
                "name": "Pauli Energy",
                "cpu_second": 0.0488922026706859,
                "calls": 214,
                "cpu_second_per_call": 0.000228468236779,
                "cpu_second_per_total": 0.005603793607928
                },
                {
                "name": "Pauli Potential",
                "cpu_second": 2.17634598945733,
                "calls": 214,
                "cpu_second_per_call": 0.010169841072231,
                "cpu_second_per_total": 0.249442509810923
                },
                {
                "name": "updateInput",
                "cpu_second": 0.762375507969409,
                "calls": 214,
                "cpu_second_per_call": 0.003562502373689,
                "cpu_second_per_total": 0.087379884010853
                }
            ]
        },
        {
            "class_name": "KEDF_vW",
            "sub": [
                {
                "name": "vw_potential",
                "cpu_second": 0.086908511002548,
                "calls": 214,
                "cpu_second_per_call": 0.000406114537395,
                "cpu_second_per_total": 0.009961043516712
                }
            ]
        },
        {
            "class_name": "PW_Basis",
            "sub": [
                {
                "name": "setup_struc_factor",
                "cpu_second": 0.000441452721133828,
                "calls": 1,
                "cpu_second_per_call": 0.000441452721134,
                "cpu_second_per_total": 0.000050597228224
                }
            ]
        },
        {
            "class_name": "PW_Basis_Sup",
            "sub": [
                {
                "name": "distributeg",
                "cpu_second": 0.000180825474672019,
                "calls": 1,
                "cpu_second_per_call": 0.000180825474672,
                "cpu_second_per_total": 0.000020725362814
                },
                {
                "name": "gatherp_scatters",
                "cpu_second": 0.0547099905088544,
                "calls": 4297,
                "cpu_second_per_call": 0.000012732136493,
                "cpu_second_per_total": 0.006270601002951
                },
                {
                "name": "gathers_scatterp",
                "cpu_second": 0.077324457350187,
                "calls": 4297,
                "cpu_second_per_call": 0.000017994986584,
                "cpu_second_per_total": 0.008862564502443
                },
                {
                "name": "real2recip",
                "cpu_second": 0.595927923452109,
                "calls": 4297,
                "cpu_second_per_call": 0.000138684645905,
                "cpu_second_per_total": 0.068302447134966
                },
                {
                "name": "recip2real",
                "cpu_second": 0.671262135729194,
                "calls": 4297,
                "cpu_second_per_call": 0.000156216461654,
                "cpu_second_per_total": 0.076936899136649
                },
                {
                "name": "setuptransform",
                "cpu_second": 0.00449420069344342,
                "calls": 1,
                "cpu_second_per_call": 0.004494200693443,
                "cpu_second_per_total": 0.000515104080876
                }
            ]
        },
        {
            "class_name": "PotLocal",
            "sub": [
                {
                "name": "cal_fixed_v",
                "cpu_second": 0.000495237181894481,
                "calls": 2,
                "cpu_second_per_call": 0.000247618590947,
                "cpu_second_per_total": 0.000056761749373
                }
            ]
        },
        {
            "class_name": "PotXC",
            "sub": [
                {
                "name": "cal_v_eff",
                "cpu_second": 1.53041711077094,
                "calls": 216,
                "cpu_second_per_call": 0.007085264401717,
                "cpu_second_per_total": 0.175409189080029
                }
            ]
        },
        {
            "class_name": "Potential",
            "sub": [
                {
                "name": "cal_fixed_v",
                "cpu_second": 0.000563273672014475,
                "calls": 2,
                "cpu_second_per_call": 0.000281636836007,
                "cpu_second_per_total": 0.000064559770890
                },
                {
                "name": "cal_v_eff",
                "cpu_second": 1.65233179100323,
                "calls": 216,
                "cpu_second_per_call": 0.007649684217608,
                "cpu_second_per_total": 0.189382474562786
                },
                {
                "name": "init_pot",
                "cpu_second": 0.019222408067435,
                "calls": 2,
                "cpu_second_per_call": 0.009611204033718,
                "cpu_second_per_total": 0.002203181725782
                },
                {
                "name": "interpolate_vrs",
                "cpu_second": 0.00319691956974566,
                "calls": 216,
                "cpu_second_per_call": 0.000014800553564,
                "cpu_second_per_total": 0.000366415838752
                },
                {
                "name": "update_from_charge",
                "cpu_second": 1.65646301500965,
                "calls": 216,
                "cpu_second_per_call": 0.007668810254674,
                "cpu_second_per_total": 0.189855975968235
                }
            ]
        },
        {
            "class_name": "Symmetry",
            "sub": [
                {
                "name": "analy_sys",
                "cpu_second": 0.0540991005254909,
                "calls": 1,
                "cpu_second_per_call": 0.054099100525491,
                "cpu_second_per_total": 0.006200583675097
                },
                {
                "name": "group fft grids",
                "cpu_second": 0.000459827366285026,
                "calls": 1,
                "cpu_second_per_call": 0.000459827366285,
                "cpu_second_per_total": 0.000052703243364
                },
                {
                "name": "rhog_symmetry",
                "cpu_second": 0.00194299465510994,
                "calls": 1,
                "cpu_second_per_call": 0.001942994655110,
                "cpu_second_per_total": 0.000222696880766
                }
            ]
        },
        {
            "class_name": "UnitCell",
            "sub": [
                {
                "name": "check_tau",
                "cpu_second": 4.8347283154726e-07,
                "calls": 1,
                "cpu_second_per_call": 0.000000483472832,
                "cpu_second_per_total": 0.000000055413375
                }
            ]
        },
        {
            "class_name": "XC_Functional",
            "sub": [
                {
                "name": "v_xc",
                "cpu_second": 5.82730702159461,
                "calls": 108,
                "cpu_second_per_call": 0.053956546496246,
                "cpu_second_per_total": 0.667898438918629
                },
                {
                "name": "v_xc_libxc",
                "cpu_second": 1.52820987382438,
                "calls": 216,
                "cpu_second_per_call": 0.007075045712150,
                "cpu_second_per_total": 0.175156205994452
                }
            ]
        },
        {
            "class_name": "mymath",
            "sub": [
                {
                "name": "heapsort",
                "cpu_second": 0.00132431648671627,
                "calls": 2,
                "cpu_second_per_call": 0.000662158243358,
                "cpu_second_per_total": 0.000151786907886
                }
            ]
        },
        {
            "class_name": "ppcell_vl",
            "sub": [
                {
                "name": "init_vloc",
                "cpu_second": 0.00602955208159983,
                "calls": 1,
                "cpu_second_per_call": 0.006029552081600,
                "cpu_second_per_total": 0.000691078813551
                }
            ]
        },
        {
            "class_name": "ppcell_vnl",
            "sub": [
                {
                "name": "init_vnl",
                "cpu_second": 3.23165440931916e-05,
                "calls": 1,
                "cpu_second_per_call": 0.000032316544093,
                "cpu_second_per_total": 0.000003703969822
                }
            ]
        }
    ]
}
