{
    "total": 427.029,
    "sub": [
        {
            "class_name": "Charge",
            "sub": [
                {
                "name": "atomic_rho",
                "cpu_second": 2.085871853,
                "calls": 2,
                "cpu_second_per_call": 1.042935926500000,
                "cpu_second_per_total": 0.004884618673530
                },
                {
                "name": "set_rho_core",
                "cpu_second": 0.000675286000000108,
                "calls": 2,
                "cpu_second_per_call": 0.000337643000000,
                "cpu_second_per_total": 0.000001581360140
                }
            ]
        },
        {
            "class_name": "Driver",
            "sub": [
                {
                "name": "driver_line",
                "cpu_second": 427.006989962,
                "calls": 1,
                "cpu_second_per_call": 427.006989961999977,
                "cpu_second_per_total": 0.999949404320426
                },
                {
                "name": "reading",
                "cpu_second": 0.021589124,
                "calls": 1,
                "cpu_second_per_call": 0.021589124000000,
                "cpu_second_per_total": 0.000050556623641
                }
            ]
        },
        {
            "class_name": "ESolver_OF",
            "sub": [
                {
                "name": "runner",
                "cpu_second": 423.577119899,
                "calls": 1,
                "cpu_second_per_call": 423.577119898999968,
                "cpu_second_per_total": 0.991917459628611
                }
            ]
        },
        {
            "class_name": "H_Ewald_pw",
            "sub": [
                {
                "name": "compute_ewald",
                "cpu_second": 0.0127823080000002,
                "calls": 1,
                "cpu_second_per_call": 0.012782308000000,
                "cpu_second_per_total": 0.000029933142948
                }
            ]
        },
        {
            "class_name": "H_Hartree_pw",
            "sub": [
                {
                "name": "v_hartree",
                "cpu_second": 28.7654254509999,
                "calls": 236,
                "cpu_second_per_call": 0.121887395978813,
                "cpu_second_per_total": 0.067361824796617
                }
            ]
        },
        {
            "class_name": "Input",
            "sub": [
                {
                "name": "Init",
                "cpu_second": 0.019918766,
                "calls": 1,
                "cpu_second_per_call": 0.019918766000000,
                "cpu_second_per_total": 0.000046645040163
                }
            ]
        },
        {
            "class_name": "Input_Conv",
            "sub": [
                {
                "name": "Convert",
                "cpu_second": 0.000347504999999998,
                "calls": 1,
                "cpu_second_per_call": 0.000347505000000,
                "cpu_second_per_total": 0.000000813774542
                }
            ]
        },
        {
            "class_name": "Ions",
            "sub": [
                {
                "name": "opt_ions",
                "cpu_second": 423.578730506,
                "calls": 1,
                "cpu_second_per_call": 423.578730505999999,
                "cpu_second_per_total": 0.991921231289376
                }
            ]
        },
        {
            "class_name": "KEDF_LKT",
            "sub": [
                {
                "name": "LKT_potential",
                "cpu_second": 137.189654002,
                "calls": 234,
                "cpu_second_per_call": 0.586280572658120,
                "cpu_second_per_total": 0.321265731060827
                }
            ]
        },
        {
            "class_name": "KEDF_vW",
            "sub": [
                {
                "name": "vw_potential",
                "cpu_second": 26.8478278279998,
                "calls": 234,
                "cpu_second_per_call": 0.114734306957264,
                "cpu_second_per_total": 0.062871264581160
                }
            ]
        },
        {
            "class_name": "PW_Basis",
            "sub": [
                {
                "name": "setup_struc_factor",
                "cpu_second": 0.037541882,
                "calls": 1,
                "cpu_second_per_call": 0.037541882000000,
                "cpu_second_per_total": 0.000087914210834
                }
            ]
        },
        {
            "class_name": "PW_Basis_Sup",
            "sub": [
                {
                "name": "distributeg",
                "cpu_second": 0.00172309,
                "calls": 1,
                "cpu_second_per_call": 0.001723090000000,
                "cpu_second_per_total": 0.000004035069354
                },
                {
                "name": "gatherp_scatters",
                "cpu_second": 14.4968369310016,
                "calls": 3059,
                "cpu_second_per_call": 0.004739077126839,
                "cpu_second_per_total": 0.033948164302827
                },
                {
                "name": "gathers_scatterp",
                "cpu_second": 17.5464966610022,
                "calls": 3059,
                "cpu_second_per_call": 0.005736023753188,
                "cpu_second_per_total": 0.041089746295818
                },
                {
                "name": "real2recip",
                "cpu_second": 151.379413810001,
                "calls": 3059,
                "cpu_second_per_call": 0.049486568751226,
                "cpu_second_per_total": 0.354494793350236
                },
                {
                "name": "recip2real",
                "cpu_second": 154.240408405999,
                "calls": 3059,
                "cpu_second_per_call": 0.050421839949657,
                "cpu_second_per_total": 0.361194566209429
                },
                {
                "name": "setuptransform",
                "cpu_second": 0.007313508,
                "calls": 1,
                "cpu_second_per_call": 0.007313508000000,
                "cpu_second_per_total": 0.000017126506451
                }
            ]
        },
        {
            "class_name": "PotLocal",
            "sub": [
                {
                "name": "cal_fixed_v",
                "cpu_second": 0.099464711,
                "calls": 2,
                "cpu_second_per_call": 0.049732355500000,
                "cpu_second_per_total": 0.000232922834645
                }
            ]
        },
        {
            "class_name": "PotXC",
            "sub": [
                {
                "name": "cal_v_eff",
                "cpu_second": 220.667828705,
                "calls": 236,
                "cpu_second_per_call": 0.935033172478813,
                "cpu_second_per_total": 0.516751877728941
                }
            ]
        },
        {
            "class_name": "Potential",
            "sub": [
                {
                "name": "cal_fixed_v",
                "cpu_second": 0.0998199749999995,
                "calls": 2,
                "cpu_second_per_call": 0.049909987500000,
                "cpu_second_per_total": 0.000233754778931
                },
                {
                "name": "cal_v_eff",
                "cpu_second": 250.687128737,
                "calls": 236,
                "cpu_second_per_call": 1.062233596343219,
                "cpu_second_per_total": 0.587049980314535
                },
                {
                "name": "init_pot",
                "cpu_second": 2.249439099,
                "calls": 2,
                "cpu_second_per_call": 1.124719549500000,
                "cpu_second_per_total": 0.005267654488045
                },
                {
                "name": "interpolate_vrs",
                "cpu_second": 0.420417453000007,
                "calls": 236,
                "cpu_second_per_call": 0.001781429885593,
                "cpu_second_per_total": 0.000984518266857
                },
                {
                "name": "update_from_charge",
                "cpu_second": 251.217720638,
                "calls": 236,
                "cpu_second_per_call": 1.064481867110170,
                "cpu_second_per_total": 0.588292501087766
                }
            ]
        },
        {
            "class_name": "Symmetry",
            "sub": [
                {
                "name": "analy_sys",
                "cpu_second": 0.062578102,
                "calls": 1,
                "cpu_second_per_call": 0.062578102000000,
                "cpu_second_per_total": 0.000146543118238
                },
                {
                "name": "group fft grids",
                "cpu_second": 0.0220199660000002,
                "calls": 1,
                "cpu_second_per_call": 0.022019966000000,
                "cpu_second_per_total": 0.000051565553732
                },
                {
                "name": "rhog_symmetry",
                "cpu_second": 0.113946531,
                "calls": 1,
                "cpu_second_per_call": 0.113946531000000,
                "cpu_second_per_total": 0.000266835832847
                }
            ]
        },
        {
            "class_name": "UnitCell",
            "sub": [
                {
                "name": "check_tau",
                "cpu_second": 9.07999999997383e-07,
                "calls": 1,
                "cpu_second_per_call": 0.000000908000000,
                "cpu_second_per_total": 0.000000002126321
                }
            ]
        },
        {
            "class_name": "XC_Functional",
            "sub": [
                {
                "name": "v_xc",
                "cpu_second": 212.384324384,
                "calls": 118,
                "cpu_second_per_call": 1.799867155796610,
                "cpu_second_per_total": 0.497353869250891
                },
                {
                "name": "v_xc_libxc",
                "cpu_second": 220.01240741,
                "calls": 236,
                "cpu_second_per_call": 0.932255963601696,
                "cpu_second_per_total": 0.515217036030981
                }
            ]
        },
        {
            "class_name": "mymath",
            "sub": [
                {
                "name": "heapsort",
                "cpu_second": 0.0278862149999999,
                "calls": 176,
                "cpu_second_per_call": 0.000158444403409,
                "cpu_second_per_total": 0.000065302921810
                }
            ]
        },
        {
            "class_name": "ppcell_vl",
            "sub": [
                {
                "name": "init_vloc",
                "cpu_second": 0.968970504,
                "calls": 1,
                "cpu_second_per_call": 0.968970504000000,
                "cpu_second_per_total": 0.002269099806458
                }
            ]
        },
        {
            "class_name": "ppcell_vnl",
            "sub": [
                {
                "name": "init_vnl",
                "cpu_second": 2.41620000001053e-05,
                "calls": 1,
                "cpu_second_per_call": 0.000024162000000,
                "cpu_second_per_total": 0.000000056581691
                }
            ]
        }
    ]
}
