{
    "total": 151.21,
    "sub": [
        {
            "class_name": "Charge",
            "sub": [
                {
                "name": "atomic_rho",
                "cpu_second": 0.0883690578630194,
                "calls": 2,
                "cpu_second_per_call": 0.044184528931510,
                "cpu_second_per_total": 0.000584413908582
                },
                {
                "name": "set_rho_core",
                "cpu_second": 0.000413532776292413,
                "calls": 2,
                "cpu_second_per_call": 0.000206766388146,
                "cpu_second_per_total": 0.000002734829498
                }
            ]
        },
        {
            "class_name": "Driver",
            "sub": [
                {
                "name": "driver_line",
                "cpu_second": 151.159974523413,
                "calls": 1,
                "cpu_second_per_call": 151.159974523412529,
                "cpu_second_per_total": 0.999671080225720
                },
                {
                "name": "reading",
                "cpu_second": 0.0497202333062887,
                "calls": 1,
                "cpu_second_per_call": 0.049720233306289,
                "cpu_second_per_total": 0.000328816404575
                }
            ]
        },
        {
            "class_name": "ESolver_OF",
            "sub": [
                {
                "name": "runner",
                "cpu_second": 147.701856589294,
                "calls": 1,
                "cpu_second_per_call": 147.701856589294039,
                "cpu_second_per_total": 0.976801398607636
                }
            ]
        },
        {
            "class_name": "H_Ewald_pw",
            "sub": [
                {
                "name": "compute_ewald",
                "cpu_second": 0.00371837161947042,
                "calls": 1,
                "cpu_second_per_call": 0.003718371619470,
                "cpu_second_per_total": 0.000024590825615
                }
            ]
        },
        {
            "class_name": "H_Hartree_pw",
            "sub": [
                {
                "name": "v_hartree",
                "cpu_second": 1.72998977004318,
                "calls": 506,
                "cpu_second_per_call": 0.003418952114710,
                "cpu_second_per_total": 0.011440996518100
                }
            ]
        },
        {
            "class_name": "Input",
            "sub": [
                {
                "name": "Init",
                "cpu_second": 0.024535283271689,
                "calls": 1,
                "cpu_second_per_call": 0.024535283271689,
                "cpu_second_per_total": 0.000162259971326
                }
            ]
        },
        {
            "class_name": "Input_Conv",
            "sub": [
                {
                "name": "Convert",
                "cpu_second": 0.000285185116808861,
                "calls": 1,
                "cpu_second_per_call": 0.000285185116809,
                "cpu_second_per_total": 0.000001886023828
                }
            ]
        },
        {
            "class_name": "Ions",
            "sub": [
                {
                "name": "opt_ions",
                "cpu_second": 147.701973315852,
                "calls": 1,
                "cpu_second_per_call": 147.701973315852229,
                "cpu_second_per_total": 0.976802170559106
                }
            ]
        },
        {
            "class_name": "KEDF_ML",
            "sub": [
                {
                "name": "Backward",
                "cpu_second": 0.314392993459478,
                "calls": 504,
                "cpu_second_per_call": 0.000623795621943,
                "cpu_second_per_total": 0.002079185210092
                },
                {
                "name": "Forward",
                "cpu_second": 2.67426296253689,
                "calls": 504,
                "cpu_second_per_call": 0.005306077306621,
                "cpu_second_per_total": 0.017685788536256
                },
                {
                "name": "Pauli Energy",
                "cpu_second": 0.636092113156337,
                "calls": 504,
                "cpu_second_per_call": 0.001262087526104,
                "cpu_second_per_total": 0.004206688257834
                },
                {
                "name": "Pauli Potential",
                "cpu_second": 86.8070888028597,
                "calls": 504,
                "cpu_second_per_call": 0.172236287307261,
                "cpu_second_per_total": 0.574084088783463
                },
                {
                "name": "updateInput",
                "cpu_second": 25.7847541700467,
                "calls": 504,
                "cpu_second_per_call": 0.051160226527870,
                "cpu_second_per_total": 0.170523137065843
                }
            ]
        },
        {
            "class_name": "KEDF_vW",
            "sub": [
                {
                "name": "vw_potential",
                "cpu_second": 1.34058079309762,
                "calls": 504,
                "cpu_second_per_call": 0.002659882525987,
                "cpu_second_per_total": 0.008865705712051
                }
            ]
        },
        {
            "class_name": "PW_Basis",
            "sub": [
                {
                "name": "setup_struc_factor",
                "cpu_second": 0.00606820359826088,
                "calls": 1,
                "cpu_second_per_call": 0.006068203598261,
                "cpu_second_per_total": 0.000040131044380
                }
            ]
        },
        {
            "class_name": "PW_Basis_Sup",
            "sub": [
                {
                "name": "distributeg",
                "cpu_second": 0.000813704275060445,
                "calls": 1,
                "cpu_second_per_call": 0.000813704275060,
                "cpu_second_per_total": 0.000005381296432
                },
                {
                "name": "gatherp_scatters",
                "cpu_second": 2.81353443622356,
                "calls": 24209,
                "cpu_second_per_call": 0.000116218531795,
                "cpu_second_per_total": 0.018606837014756
                },
                {
                "name": "gathers_scatterp",
                "cpu_second": 4.10153879981954,
                "calls": 24209,
                "cpu_second_per_call": 0.000169422066166,
                "cpu_second_per_total": 0.027124837348846
                },
                {
                "name": "real2recip",
                "cpu_second": 21.3234106499003,
                "calls": 24209,
                "cpu_second_per_call": 0.000880805099339,
                "cpu_second_per_total": 0.141018791685367
                },
                {
                "name": "recip2real",
                "cpu_second": 25.0976101004635,
                "calls": 24209,
                "cpu_second_per_call": 0.001036705774731,
                "cpu_second_per_total": 0.165978825276451
                },
                {
                "name": "setuptransform",
                "cpu_second": 0.00560683797812089,
                "calls": 1,
                "cpu_second_per_call": 0.005606837978121,
                "cpu_second_per_total": 0.000037079880411
                }
            ]
        },
        {
            "class_name": "PotLocal",
            "sub": [
                {
                "name": "cal_fixed_v",
                "cpu_second": 0.00429600436473265,
                "calls": 2,
                "cpu_second_per_call": 0.002148002182366,
                "cpu_second_per_total": 0.000028410902671
                }
            ]
        },
        {
            "class_name": "PotXC",
            "sub": [
                {
                "name": "cal_v_eff",
                "cpu_second": 21.754979950143,
                "calls": 506,
                "cpu_second_per_call": 0.042994031522022,
                "cpu_second_per_total": 0.143872902702031
                }
            ]
        },
        {
            "class_name": "Potential",
            "sub": [
                {
                "name": "cal_fixed_v",
                "cpu_second": 0.00464595039375126,
                "calls": 2,
                "cpu_second_per_call": 0.002322975196876,
                "cpu_second_per_total": 0.000030725211905
                },
                {
                "name": "cal_v_eff",
                "cpu_second": 23.579690945975,
                "calls": 506,
                "cpu_second_per_call": 0.046600179735128,
                "cpu_second_per_total": 0.155940322123437
                },
                {
                "name": "init_pot",
                "cpu_second": 0.116848930541892,
                "calls": 2,
                "cpu_second_per_call": 0.058424465270946,
                "cpu_second_per_total": 0.000772760758834
                },
                {
                "name": "interpolate_vrs",
                "cpu_second": 0.0611422135843895,
                "calls": 506,
                "cpu_second_per_call": 0.000120834414198,
                "cpu_second_per_total": 0.000404353751011
                },
                {
                "name": "update_from_charge",
                "cpu_second": 23.6473502549925,
                "calls": 506,
                "cpu_second_per_call": 0.046733893784570,
                "cpu_second_per_total": 0.156387775589515
                }
            ]
        },
        {
            "class_name": "Symmetry",
            "sub": [
                {
                "name": "analy_sys",
                "cpu_second": 0.0500984433456324,
                "calls": 1,
                "cpu_second_per_call": 0.050098443345632,
                "cpu_second_per_total": 0.000331317633089
                },
                {
                "name": "group fft grids",
                "cpu_second": 0.00222519767703488,
                "calls": 1,
                "cpu_second_per_call": 0.002225197677035,
                "cpu_second_per_total": 0.000014715970762
                },
                {
                "name": "rhog_symmetry",
                "cpu_second": 0.00868031941354275,
                "calls": 1,
                "cpu_second_per_call": 0.008680319413543,
                "cpu_second_per_total": 0.000057405833206
                }
            ]
        },
        {
            "class_name": "UnitCell",
            "sub": [
                {
                "name": "check_tau",
                "cpu_second": 4.28699422627687e-07,
                "calls": 1,
                "cpu_second_per_call": 0.000000428699423,
                "cpu_second_per_total": 0.000000002835132
                }
            ]
        },
        {
            "class_name": "XC_Functional",
            "sub": [
                {
                "name": "v_xc",
                "cpu_second": 77.0268237043056,
                "calls": 253,
                "cpu_second_per_call": 0.304453848633619,
                "cpu_second_per_total": 0.509403949700407
                },
                {
                "name": "v_xc_libxc",
                "cpu_second": 21.7075907551916,
                "calls": 506,
                "cpu_second_per_call": 0.042900376986545,
                "cpu_second_per_total": 0.143559502227749
                }
            ]
        },
        {
            "class_name": "mymath",
            "sub": [
                {
                "name": "heapsort",
                "cpu_second": 0.00873026641784236,
                "calls": 2,
                "cpu_second_per_call": 0.004365133208921,
                "cpu_second_per_total": 0.000057736149322
                }
            ]
        },
        {
            "class_name": "ppcell_vl",
            "sub": [
                {
                "name": "init_vloc",
                "cpu_second": 0.0375120679964311,
                "calls": 1,
                "cpu_second_per_call": 0.037512067996431,
                "cpu_second_per_total": 0.000248079755595
                }
            ]
        },
        {
            "class_name": "ppcell_vnl",
            "sub": [
                {
                "name": "init_vnl",
                "cpu_second": 2.61242967098951e-05,
                "calls": 1,
                "cpu_second_per_call": 0.000026124296710,
                "cpu_second_per_total": 0.000000172768645
                }
            ]
        }
    ]
}
