{
    "total": 103.061,
    "sub": [
        {
            "class_name": "Charge",
            "sub": [
                {
                "name": "atomic_rho",
                "cpu_second": 0.329674080596305,
                "calls": 2,
                "cpu_second_per_call": 0.164837040298153,
                "cpu_second_per_total": 0.003198839786564
                },
                {
                "name": "set_rho_core",
                "cpu_second": 0.000439460389316082,
                "calls": 2,
                "cpu_second_per_call": 0.000219730194658,
                "cpu_second_per_total": 0.000004264100397
                }
            ]
        },
        {
            "class_name": "Driver",
            "sub": [
                {
                "name": "driver_line",
                "cpu_second": 103.025492835441,
                "calls": 1,
                "cpu_second_per_call": 103.025492835440673,
                "cpu_second_per_total": 0.999660164111966
                },
                {
                "name": "reading",
                "cpu_second": 0.0350212594494224,
                "calls": 1,
                "cpu_second_per_call": 0.035021259449422,
                "cpu_second_per_total": 0.000339812574588
                }
            ]
        },
        {
            "class_name": "ESolver_OF",
            "sub": [
                {
                "name": "runner",
                "cpu_second": 99.0865581573453,
                "calls": 1,
                "cpu_second_per_call": 99.086558157345280,
                "cpu_second_per_total": 0.961440535373857
                }
            ]
        },
        {
            "class_name": "H_Ewald_pw",
            "sub": [
                {
                "name": "compute_ewald",
                "cpu_second": 0.00344100932125002,
                "calls": 1,
                "cpu_second_per_call": 0.003441009321250,
                "cpu_second_per_total": 0.000033388240601
                }
            ]
        },
        {
            "class_name": "H_Hartree_pw",
            "sub": [
                {
                "name": "v_hartree",
                "cpu_second": 2.5363536789082,
                "calls": 612,
                "cpu_second_per_call": 0.004144368756386,
                "cpu_second_per_total": 0.024610333473029
                }
            ]
        },
        {
            "class_name": "Input",
            "sub": [
                {
                "name": "Init",
                "cpu_second": 0.0309437566902488,
                "calls": 1,
                "cpu_second_per_call": 0.030943756690249,
                "cpu_second_per_total": 0.000300248414639
                }
            ]
        },
        {
            "class_name": "Input_Conv",
            "sub": [
                {
                "name": "Convert",
                "cpu_second": 0.00029574241489172,
                "calls": 1,
                "cpu_second_per_call": 0.000295742414892,
                "cpu_second_per_total": 0.000002869599580
                }
            ]
        },
        {
            "class_name": "Ions",
            "sub": [
                {
                "name": "opt_ions",
                "cpu_second": 99.0866780296201,
                "calls": 1,
                "cpu_second_per_call": 99.086678029620089,
                "cpu_second_per_total": 0.961441698498970
                }
            ]
        },
        {
            "class_name": "KEDF_ML",
            "sub": [
                {
                "name": "Backward",
                "cpu_second": 0.378178039914928,
                "calls": 610,
                "cpu_second_per_call": 0.000619963999861,
                "cpu_second_per_total": 0.003669475496213
                },
                {
                "name": "Forward",
                "cpu_second": 1.07328703533858,
                "calls": 610,
                "cpu_second_per_call": 0.001759486943178,
                "cpu_second_per_total": 0.010414143765365
                },
                {
                "name": "Pauli Energy",
                "cpu_second": 0.814085900201462,
                "calls": 610,
                "cpu_second_per_call": 0.001334567049511,
                "cpu_second_per_total": 0.007899105572797
                },
                {
                "name": "Pauli Potential",
                "cpu_second": 40.1686056808103,
                "calls": 610,
                "cpu_second_per_call": 0.065850173247230,
                "cpu_second_per_total": 0.389757465282558
                },
                {
                "name": "updateInput",
                "cpu_second": 14.992472153157,
                "calls": 610,
                "cpu_second_per_call": 0.024577823201897,
                "cpu_second_per_total": 0.145472511323075
                }
            ]
        },
        {
            "class_name": "KEDF_vW",
            "sub": [
                {
                "name": "vw_potential",
                "cpu_second": 2.02492632321082,
                "calls": 610,
                "cpu_second_per_call": 0.003319551349526,
                "cpu_second_per_total": 0.019647934941780
                }
            ]
        },
        {
            "class_name": "PW_Basis",
            "sub": [
                {
                "name": "setup_struc_factor",
                "cpu_second": 0.00470030622091144,
                "calls": 1,
                "cpu_second_per_call": 0.004700306220911,
                "cpu_second_per_total": 0.000045607244953
                }
            ]
        },
        {
            "class_name": "PW_Basis_Sup",
            "sub": [
                {
                "name": "distributeg",
                "cpu_second": 0.00089967017993331,
                "calls": 1,
                "cpu_second_per_call": 0.000899670179933,
                "cpu_second_per_total": 0.000008729533002
                },
                {
                "name": "gatherp_scatters",
                "cpu_second": 1.97226659650914,
                "calls": 12217,
                "cpu_second_per_call": 0.000161436244291,
                "cpu_second_per_total": 0.019136975667644
                },
                {
                "name": "gathers_scatterp",
                "cpu_second": 2.36467906925827,
                "calls": 12217,
                "cpu_second_per_call": 0.000193556443420,
                "cpu_second_per_total": 0.022944568391656
                },
                {
                "name": "real2recip",
                "cpu_second": 13.8904993967153,
                "calls": 12217,
                "cpu_second_per_call": 0.001136981206247,
                "cpu_second_per_total": 0.134780028945815
                },
                {
                "name": "recip2real",
                "cpu_second": 15.2729508223711,
                "calls": 12217,
                "cpu_second_per_call": 0.001250139217678,
                "cpu_second_per_total": 0.148194006215065
                },
                {
                "name": "setuptransform",
                "cpu_second": 0.00562207738403231,
                "calls": 1,
                "cpu_second_per_call": 0.005622077384032,
                "cpu_second_per_total": 0.000054551224611
                }
            ]
        },
        {
            "class_name": "PotLocal",
            "sub": [
                {
                "name": "cal_fixed_v",
                "cpu_second": 0.00427820812910795,
                "calls": 2,
                "cpu_second_per_call": 0.002139104064554,
                "cpu_second_per_total": 0.000041511611571
                }
            ]
        },
        {
            "class_name": "PotXC",
            "sub": [
                {
                "name": "cal_v_eff",
                "cpu_second": 30.0765743486118,
                "calls": 612,
                "cpu_second_per_call": 0.049144729327797,
                "cpu_second_per_total": 0.291834112332595
                }
            ]
        },
        {
            "class_name": "Potential",
            "sub": [
                {
                "name": "cal_fixed_v",
                "cpu_second": 0.00465904956217855,
                "calls": 2,
                "cpu_second_per_call": 0.002329524781089,
                "cpu_second_per_total": 0.000045206930069
                },
                {
                "name": "cal_v_eff",
                "cpu_second": 32.746056396747,
                "calls": 612,
                "cpu_second_per_call": 0.053506628099260,
                "cpu_second_per_total": 0.317736195291764
                },
                {
                "name": "init_pot",
                "cpu_second": 0.136167013784871,
                "calls": 2,
                "cpu_second_per_call": 0.068083506892435,
                "cpu_second_per_total": 0.001321233566572
                },
                {
                "name": "interpolate_vrs",
                "cpu_second": 0.0743606998585165,
                "calls": 612,
                "cpu_second_per_call": 0.000121504411534,
                "cpu_second_per_total": 0.000721524618599
                },
                {
                "name": "update_from_charge",
                "cpu_second": 32.8274243624182,
                "calls": 612,
                "cpu_second_per_call": 0.053639582291533,
                "cpu_second_per_total": 0.318525711669485
                }
            ]
        },
        {
            "class_name": "Symmetry",
            "sub": [
                {
                "name": "analy_sys",
                "cpu_second": 0.040815590065904,
                "calls": 1,
                "cpu_second_per_call": 0.040815590065904,
                "cpu_second_per_total": 0.000396035178679
                },
                {
                "name": "group fft grids",
                "cpu_second": 0.00272747350391001,
                "calls": 1,
                "cpu_second_per_call": 0.002727473503910,
                "cpu_second_per_total": 0.000026464776198
                },
                {
                "name": "rhog_symmetry",
                "cpu_second": 0.0115024009719491,
                "calls": 1,
                "cpu_second_per_call": 0.011502400971949,
                "cpu_second_per_total": 0.000111608221682
                }
            ]
        },
        {
            "class_name": "UnitCell",
            "sub": [
                {
                "name": "check_tau",
                "cpu_second": 6.02216459810734e-07,
                "calls": 1,
                "cpu_second_per_call": 0.000000602216460,
                "cpu_second_per_total": 0.000000005843329
                }
            ]
        },
        {
            "class_name": "XC_Functional",
            "sub": [
                {
                "name": "v_xc",
                "cpu_second": 53.0125916417455,
                "calls": 306,
                "cpu_second_per_call": 0.173243763535116,
                "cpu_second_per_total": 0.514383135688897
                },
                {
                "name": "v_xc_libxc",
                "cpu_second": 30.0158650323283,
                "calls": 612,
                "cpu_second_per_call": 0.049045531098576,
                "cpu_second_per_total": 0.291245047593288
                }
            ]
        },
        {
            "class_name": "mymath",
            "sub": [
                {
                "name": "heapsort",
                "cpu_second": 0.010033106431365,
                "calls": 61,
                "cpu_second_per_call": 0.000164477154613,
                "cpu_second_per_total": 0.000097351602460
                }
            ]
        },
        {
            "class_name": "ppcell_vl",
            "sub": [
                {
                "name": "init_vloc",
                "cpu_second": 0.155000730068423,
                "calls": 1,
                "cpu_second_per_call": 0.155000730068423,
                "cpu_second_per_total": 0.001503977811639
                }
            ]
        },
        {
            "class_name": "ppcell_vnl",
            "sub": [
                {
                "name": "init_vnl",
                "cpu_second": 3.87214822694659e-05,
                "calls": 1,
                "cpu_second_per_call": 0.000038721482269,
                "cpu_second_per_total": 0.000000375715973
                }
            ]
        }
    ]
}
